favihunter/__init__.py
favihunter/collectors/__init__.py
favihunter/collectors/collector_functions.py
favihunter/engines.yaml
favihunter/favihunter.py
favihunter/printers/__init__.py
favihunter/printers/printing_functions.py
favihunter/utils/__init__.py
favihunter/utils/utils.py
favihunter/virustotal/__init__.py
favihunter/virustotal/vt.py
favihunter-1.3.2.dist-info/LICENSE
favihunter-1.3.2.dist-info/METADATA
favihunter-1.3.2.dist-info/WHEEL
favihunter-1.3.2.dist-info/entry_points.txt
favihunter-1.3.2.dist-info/RECORD
