Metadata-Version: 2.1
Name: favihunter
Version: 1.3.2
Summary: Discover and monitor internet assets using favicon hashes across search engines.
Home-page: https://github.com/eremit4/favihunter
License: MIT
Author: eremit4
Author-email: eremit4@protonmail.com
Requires-Python: >=3.8,<4.0
Classifier: License :: OSI Approved :: MIT License
Classifier: Programming Language :: Python :: 3
Classifier: Programming Language :: Python :: 3.8
Classifier: Programming Language :: Python :: 3.9
Classifier: Programming Language :: Python :: 3.10
Classifier: Programming Language :: Python :: 3.11
Classifier: Programming Language :: Python :: 3.12
Requires-Dist: PyYAML (==6.0.2)
Requires-Dist: colorama (==0.4.6)
Requires-Dist: favicon (==0.7.0)
Requires-Dist: mmh3 (==4.0.1)
Requires-Dist: pillow (==10.4.0)
Requires-Dist: requests (>=2.32.4,<2.33.0)
Project-URL: Repository, https://github.com/eremit4/favihunter
